decochators/__init__.py
decochators/core/__init__.py
decochators/dimensions/__init__.py
decochators/dimensions/one_dimension/__init__.py
decochators/dimensions/one_dimension/attach_chaos_1d.py
decochators/dimensions/three_dimensions/__init__.py
decochators/dimensions/three_dimensions/attach_chaos_3d.py
decochators/helpers/__init__.py
decochators/helpers/core_1d.py
decochators/helpers/core_3d.py
decochators-1.1.0.dist-info/METADATA
decochators-1.1.0.dist-info/WHEEL
decochators-1.1.0.dist-info/top_level.txt
decochators-1.1.0.dist-info/RECORD
