Metadata-Version: 2.4
Name: decochators
Version: 1.1.0
Summary: Library for analysis and visualization of chaotic systems
Home-page: https://github.com/yoshlsec/decochators
Author: yoshl
Author-email: yoshlconele@gmail.com
License: MIT
Classifier: Programming Language :: Python :: 3
Classifier: License :: OSI Approved :: MIT License
Classifier: Operating System :: OS Independent
Requires-Python: >=3.8
Requires-Dist: numpy==2.3.1
Requires-Dist: matplotlib==3.10.3
Requires-Dist: scipy==1.16.0
